README.md
setup.cfg
setup.py
cv2routine/__init__.py
cv2routine/color_filter.py
cv2routine/figures.py
cv2routine/test.py
cv2routine/transform.py
cv2routine.egg-info/PKG-INFO
cv2routine.egg-info/SOURCES.txt
cv2routine.egg-info/dependency_links.txt
cv2routine.egg-info/not-zip-safe
cv2routine.egg-info/requires.txt
cv2routine.egg-info/top_level.txt