Metadata-Version: 2.1
Name: cv2routine
Version: 0.0.3
Summary: Helps with routines in OpenCV
Home-page: https://github.com/KAD1605/cv2routine
Author: Klinovitskij Andrey
Author-email: adk160501@gmail.com
License: MIT
Keywords: opencv,cv2,routine,image processing,computer vision,cv2routine
